<?xml version="1.0" encoding="UTF-8"?><record_update sys_domain="global" table="sys_hub_flow">
    <sys_hub_flow action="DELETE">
        <access>public</access>
        <acls/>
        <active>false</active>
        <annotation/>
        <attributes>labelCacheCleanUpExecuted=true</attributes>
        <authored_on_release_version>25000</authored_on_release_version>
        <callable_by_client_api>false</callable_by_client_api>
        <category/>
        <compiler_build/>
        <copied_from/>
        <copied_from_name/>
        <description/>
        <display_name_after_preview/>
        <flow_priority>MEDIUM</flow_priority>
        <generation_source/>
        <internal_name>inspection</internal_name>
        <label_cache>null</label_cache>
        <latest_snapshot/>
        <master_snapshot/>
        <name>inspection</name>
        <natlang/>
        <outputs/>
        <pre_compiled>false</pre_compiled>
        <remote_trigger_id/>
        <run_as>user</run_as>
        <run_with_roles/>
        <sc_callable>false</sc_callable>
        <show_draft_actions>false</show_draft_actions>
        <show_triggered_flows>false</show_triggered_flows>
        <status>draft</status>
        <substatus/>
        <sys_class_name>sys_hub_flow</sys_class_name>
        <sys_created_by>admin</sys_created_by>
        <sys_created_on>2024-10-19 14:14:42</sys_created_on>
        <sys_domain>global</sys_domain>
        <sys_domain_path>/</sys_domain_path>
        <sys_id>8c701ad28355121008b7c596feaad36d</sys_id>
        <sys_mod_count>0</sys_mod_count>
        <sys_name>inspection</sys_name>
        <sys_overrides/>
        <sys_package display_value="Property Management Ltd" source="x_1542827_proper_0">9caa27a983d1121008b7c596feaad301</sys_package>
        <sys_policy/>
        <sys_scope display_value="Property Management Ltd">9caa27a983d1121008b7c596feaad301</sys_scope>
        <sys_update_name>sys_hub_flow_8c701ad28355121008b7c596feaad36d</sys_update_name>
        <sys_updated_by>admin</sys_updated_by>
        <sys_updated_on>2024-10-19 14:14:42</sys_updated_on>
        <type>flow</type>
    </sys_hub_flow>
    <sys_translated_text action="DELETE" query="documentkey=8c701ad28355121008b7c596feaad36d"/>
    <sys_variable_value action="DELETE" query="document_key=8c701ad28355121008b7c596feaad36d"/>
    <sys_hub_trigger_instance action="DELETE" query="flow=8c701ad28355121008b7c596feaad36d"/>
    <sys_hub_flow_stage action="DELETE" query="flow=8c701ad28355121008b7c596feaad36d"/>
    <sys_flow_cat_variable_model action="DELETE" query="id=8c701ad28355121008b7c596feaad36d^sys_idNOT IN84701ad28355121008b7c596feaad36e"/>
    <sys_flow_cat_variable_model action="DELETE">
        <id>8c701ad28355121008b7c596feaad36d</id>
        <name>inspection</name>
        <sys_created_by>admin</sys_created_by>
        <sys_created_on>2024-10-19 14:14:42</sys_created_on>
        <sys_id>84701ad28355121008b7c596feaad36e</sys_id>
        <sys_mod_count>0</sys_mod_count>
        <sys_scope/>
        <sys_updated_by>admin</sys_updated_by>
        <sys_updated_on>2024-10-19 14:14:42</sys_updated_on>
    </sys_flow_cat_variable_model>
    <sys_flow_cat_variable action="DELETE" query="flow_catalog_model=84701ad28355121008b7c596feaad36e"/>
    <sys_hub_flow_input action="DELETE" query="model=8c701ad28355121008b7c596feaad36d"/>
    <sys_hub_flow_output action="DELETE" query="model=8c701ad28355121008b7c596feaad36d"/>
    <sys_hub_alias_mapping action="DELETE" query="source_id=8c701ad28355121008b7c596feaad36d"/>
    <sys_hub_action_instance action="DELETE" query="flow=8c701ad28355121008b7c596feaad36d"/>
    <sys_hub_sub_flow_instance action="DELETE" query="flow=8c701ad28355121008b7c596feaad36d"/>
    <sys_hub_flow_logic action="DELETE" query="flow=8c701ad28355121008b7c596feaad36d"/>
    <sys_hub_pill_compound action="DELETE" query="attached_to=8c701ad28355121008b7c596feaad36d"/>
    <sys_hub_flow_variable action="DELETE" query="model=8c701ad28355121008b7c596feaad36d"/>
    <sys_documentation action="DELETE" query="name=var__m_sys_hub_flow_input_8c701ad28355121008b7c596feaad36d"/>
    <sys_choice action="DELETE" query="name=var__m_sys_hub_flow_input_8c701ad28355121008b7c596feaad36d"/>
    <sys_documentation action="DELETE" query="name=var__m_sys_hub_flow_output_8c701ad28355121008b7c596feaad36d"/>
    <sys_choice action="DELETE" query="name=var__m_sys_hub_flow_output_8c701ad28355121008b7c596feaad36d"/>
    <sys_flow_trigger_plan action="DELETE" query="plan_id=8c701ad28355121008b7c596feaad36d"/>
    <sys_flow_subflow_plan action="DELETE" query="plan_id=8c701ad28355121008b7c596feaad36d"/>
    <sys_update_version action="INSERT_OR_UPDATE">
        <action>DELETE</action>
        <application display_value="Property Management Ltd">9caa27a983d1121008b7c596feaad301</application>
        <file_path/>
        <instance_id>4d4b0ac61b9a869039a54089bd4bcbf1</instance_id>
        <instance_name>dev272968</instance_name>
        <name>sys_hub_flow_8c701ad28355121008b7c596feaad36d</name>
        <payload><![CDATA[<?xml version="1.0" encoding="UTF-8"?><record_update sys_domain="global" table="sys_hub_flow"><sys_hub_flow action="INSERT_OR_UPDATE"><access>public</access><acls/><active>false</active><annotation/><attributes>labelCacheCleanUpExecuted=true</attributes><authored_on_release_version>25000</authored_on_release_version><callable_by_client_api>false</callable_by_client_api><category/><compiler_build/><copied_from/><copied_from_name/><description/><display_name_after_preview/><flow_priority>MEDIUM</flow_priority><generation_source/><internal_name>inspection</internal_name><label_cache>null</label_cache><latest_snapshot/><master_snapshot/><name>inspection</name><natlang/><outputs/><pre_compiled>false</pre_compiled><remote_trigger_id/><run_as>user</run_as><run_with_roles/><sc_callable>false</sc_callable><show_draft_actions>false</show_draft_actions><show_triggered_flows>false</show_triggered_flows><status>draft</status><substatus/><sys_class_name>sys_hub_flow</sys_class_name><sys_created_by>admin</sys_created_by><sys_created_on>2024-10-19 14:14:42</sys_created_on><sys_domain>global</sys_domain><sys_domain_path>/</sys_domain_path><sys_id>8c701ad28355121008b7c596feaad36d</sys_id><sys_mod_count>0</sys_mod_count><sys_name>inspection</sys_name><sys_overrides/><sys_package display_value="Property Management Ltd" source="x_1542827_proper_0">9caa27a983d1121008b7c596feaad301</sys_package><sys_policy/><sys_scope display_value="Property Management Ltd">9caa27a983d1121008b7c596feaad301</sys_scope><sys_update_name>sys_hub_flow_8c701ad28355121008b7c596feaad36d</sys_update_name><sys_updated_by>admin</sys_updated_by><sys_updated_on>2024-10-19 14:14:42</sys_updated_on><type>flow</type></sys_hub_flow><sys_translated_text action="delete_multiple" query="documentkey=8c701ad28355121008b7c596feaad36d"/><sys_variable_value action="delete_multiple" query="document_key=8c701ad28355121008b7c596feaad36d"/><sys_hub_trigger_instance action="delete_multiple" query="flow=8c701ad28355121008b7c596feaad36d"/><sys_hub_flow_stage action="delete_multiple" query="flow=8c701ad28355121008b7c596feaad36d"/><sys_flow_cat_variable_model action="delete_multiple" query="id=8c701ad28355121008b7c596feaad36d^sys_idNOT IN84701ad28355121008b7c596feaad36e"/><sys_flow_cat_variable_model action="INSERT_OR_UPDATE"><id>8c701ad28355121008b7c596feaad36d</id><name>inspection</name><sys_created_by>admin</sys_created_by><sys_created_on>2024-10-19 14:14:42</sys_created_on><sys_id>84701ad28355121008b7c596feaad36e</sys_id><sys_mod_count>0</sys_mod_count><sys_scope/><sys_updated_by>admin</sys_updated_by><sys_updated_on>2024-10-19 14:14:42</sys_updated_on></sys_flow_cat_variable_model><sys_flow_cat_variable action="delete_multiple" query="flow_catalog_model=84701ad28355121008b7c596feaad36e"/><sys_hub_flow_input action="delete_multiple" query="model=8c701ad28355121008b7c596feaad36d"/><sys_hub_flow_output action="delete_multiple" query="model=8c701ad28355121008b7c596feaad36d"/><sys_hub_alias_mapping action="delete_multiple" query="source_id=8c701ad28355121008b7c596feaad36d"/><sys_hub_action_instance action="delete_multiple" query="flow=8c701ad28355121008b7c596feaad36d"/><sys_hub_sub_flow_instance action="delete_multiple" query="flow=8c701ad28355121008b7c596feaad36d"/><sys_hub_flow_logic action="delete_multiple" query="flow=8c701ad28355121008b7c596feaad36d"/><sys_hub_pill_compound action="delete_multiple" query="attached_to=8c701ad28355121008b7c596feaad36d"/><sys_hub_flow_variable action="delete_multiple" query="model=8c701ad28355121008b7c596feaad36d"/><sys_documentation action="delete_multiple" query="name=var__m_sys_hub_flow_input_8c701ad28355121008b7c596feaad36d"/><sys_choice action="delete_multiple" query="name=var__m_sys_hub_flow_input_8c701ad28355121008b7c596feaad36d"/><sys_documentation action="delete_multiple" query="name=var__m_sys_hub_flow_output_8c701ad28355121008b7c596feaad36d"/><sys_choice action="delete_multiple" query="name=var__m_sys_hub_flow_output_8c701ad28355121008b7c596feaad36d"/><sys_flow_trigger_plan action="delete_multiple" query="plan_id=8c701ad28355121008b7c596feaad36d"/><sys_flow_subflow_plan action="delete_multiple" query="plan_id=8c701ad28355121008b7c596feaad36d"/></record_update>]]></payload>
        <payload_hash>-1659407351</payload_hash>
        <record_name>inspection</record_name>
        <reverted_from/>
        <source>c359f43d8351521008b7c596feaad3d9</source>
        <source_table>sys_update_set</source_table>
        <state>previous</state>
        <sys_created_by>admin</sys_created_by>
        <sys_created_on>2024-10-19 14:14:42</sys_created_on>
        <sys_id>c070129283d5121008b7c596feaad386</sys_id>
        <sys_mod_count>0</sys_mod_count>
        <sys_recorded_at>192a52167760000001</sys_recorded_at>
        <sys_updated_by>admin</sys_updated_by>
        <sys_updated_on>2024-10-19 14:14:42</sys_updated_on>
        <type>Flow</type>
        <update_guid>04701ad22a551210d6c0c4c5197e0a72</update_guid>
        <update_guid_history>04701ad22a551210d6c0c4c5197e0a72:-1659407351</update_guid_history>
    </sys_update_version>
    <sys_metadata_delete action="INSERT_OR_UPDATE">
        <sys_audit_delete/>
        <sys_class_name>sys_metadata_delete</sys_class_name>
        <sys_created_by>admin</sys_created_by>
        <sys_created_on>2024-10-19 14:40:29</sys_created_on>
        <sys_db_object display_value="" name="sys_hub_flow">sys_hub_flow</sys_db_object>
        <sys_id>03fa24d4c36a4aa980e9fa53bbd017e1</sys_id>
        <sys_metadata>8c701ad28355121008b7c596feaad36d</sys_metadata>
        <sys_mod_count>0</sys_mod_count>
        <sys_name>inspection</sys_name>
        <sys_package display_value="Property Management Ltd" source="x_1542827_proper_0">9caa27a983d1121008b7c596feaad301</sys_package>
        <sys_parent/>
        <sys_policy/>
        <sys_scope display_value="Property Management Ltd">9caa27a983d1121008b7c596feaad301</sys_scope>
        <sys_scope_delete display_value="">2ed4618112eb4004a458ccae47dadd90</sys_scope_delete>
        <sys_update_name>sys_hub_flow_8c701ad28355121008b7c596feaad36d</sys_update_name>
        <sys_update_version display_value="sys_hub_flow_8c701ad28355121008b7c596feaad36d">c070129283d5121008b7c596feaad386</sys_update_version>
        <sys_updated_by>admin</sys_updated_by>
        <sys_updated_on>2024-10-19 14:40:29</sys_updated_on>
    </sys_metadata_delete>
</record_update>
